<?xml version="1.0" encoding="UTF-8"?>
<!DOCTYPE suite SYSTEM "https://testng.org/testng-1.0.dtd">
<suite name="Suite">
  <test thread-count="5" name="Test">
    <classes>
      <class name="testCases.IframeTest"/>
      <class name="testCases.FloatingMenuTest"/>
      <class name="testCases.JavaScriptErrorTest"/>
      <class name="testCases.JavaScriptAlertsTest"/>
      <class name="testCases.BaseTest"/>
      <class name="testCases.OpeningNewTabTest"/>
      <class name="testCases.LoginTest"/>
      <class name="testCases.CheckBoxesTest"/>
      <class name="testCases.FileDownloadTest"/>
      <class name="testCases.FileUploadTest"/>
      <class name="testCases.DynamicLoadingTest"/>
      <class name="testCases.DynamicContentTest"/>
      <class name="testCases.DropdownTest"/>
      <class name="testCases.NotificationMessageTest"/>
      <class name="testCases.ContextMenuTest"/>
      <class name="testCases.DragAndDropTest"/>
      <class name="testCases.DynamicControlsTest"/>
      <class name="testCases.MouseHoverTest"/>
    </classes>
  </test> <!-- Test -->
</suite> <!-- Suite -->
